google_address_to_latlong_csv/__init__.py
google_address_to_latlong_csv/input_file.csv
google_address_to_latlong_csv-0.1.4.dist-info/LICENSE
google_address_to_latlong_csv-0.1.4.dist-info/WHEEL
google_address_to_latlong_csv-0.1.4.dist-info/METADATA
google_address_to_latlong_csv-0.1.4.dist-info/RECORD
